setup.py
fake2db/__init__.py
fake2db/base_handler.py
fake2db/couchdb_handler.py
fake2db/custom.py
fake2db/fake2db.py
fake2db/helpers.py
fake2db/mongodb_handler.py
fake2db/mysql_handler.py
fake2db/postgresql_handler.py
fake2db/redis_handler.py
fake2db/sqlite_handler.py
fake2db.egg-info/PKG-INFO
fake2db.egg-info/SOURCES.txt
fake2db.egg-info/dependency_links.txt
fake2db.egg-info/entry_points.txt
fake2db.egg-info/requires.txt
fake2db.egg-info/top_level.txt