Metadata-Version: 1.1
Name: fake2db
Version: 0.5.4
Summary: Generate test databases filled with fake data (NOW CUSTOM SCHEMA CREATION SUPPORTED)(current support - sqlite, mysql, postgresql, mongodb, redis, couchdb)
Home-page: https://github.com/emirozer/fake2db
Author: Emir Ozer
Author-email: emirozer@yandex.com
License: UNKNOWN
Platform: UNKNOWN
Classifier: Development Status :: 5 - Production/Stable
Classifier: Environment :: Console
Classifier: Intended Audience :: Developers
Classifier: License :: OSI Approved :: GNU General Public License v2 (GPLv2)
Classifier: Operating System :: OS Independent
Classifier: Programming Language :: Python
